LICENSE
README.rst
setup.py
crystalpy/__init__.py
crystalpy.egg-info/PKG-INFO
crystalpy.egg-info/SOURCES.txt
crystalpy.egg-info/dependency_links.txt
crystalpy.egg-info/requires.txt
crystalpy.egg-info/top_level.txt
crystalpy/diffraction/Diffraction.py
crystalpy/diffraction/DiffractionExceptions.py
crystalpy/diffraction/DiffractionResult.py
crystalpy/diffraction/DiffractionSetupAbstract.py
crystalpy/diffraction/DiffractionSetupDabax.py
crystalpy/diffraction/DiffractionSetupShadowPreprocessorV1.py
crystalpy/diffraction/DiffractionSetupShadowPreprocessorV2.py
crystalpy/diffraction/DiffractionSetupSweeps.py
crystalpy/diffraction/DiffractionSetupXraylib.py
crystalpy/diffraction/GeometryType.py
crystalpy/diffraction/PerfectCrystalDiffraction.py
crystalpy/diffraction/Xiaojiang_DiffractionSetupShadowPreprocessorV2.py
crystalpy/diffraction/__init__.py
crystalpy/polarization/CrystalPhasePlate.py
crystalpy/polarization/MuellerDiffraction.py
crystalpy/polarization/MuellerMatrix.py
crystalpy/polarization/MuellerResult.py
crystalpy/polarization/__init__.py
crystalpy/util/CalculationStrategy.py
crystalpy/util/ComplexAmplitudePhoton.py
crystalpy/util/ComplexAmplitudePhotonBunch.py
crystalpy/util/Photon.py
crystalpy/util/PhotonBunch.py
crystalpy/util/PlotData1D.py
crystalpy/util/PolarizedPhoton.py
crystalpy/util/PolarizedPhotonBunch.py
crystalpy/util/StokesVector.py
crystalpy/util/Vector.py
crystalpy/util/__init__.py
crystalpy/util/bragg_preprocessor_file_io.py
crystalpy/util/calc_xcrystal.py