Metadata-Version: 2.1
Name: crystalpy
Version: 0.0.25
Summary: Python crystal polarization calculation
Home-page: https://github.com/oasys-kit/crystalpy/
Author: Manuel Sanchez del Rio, Edoardo Cappelli, Mark Glass
Author-email: srio@esrf.eu
License-File: LICENSE
Requires-Dist: numpy
Requires-Dist: scipy
Requires-Dist: mpmath
Requires-Dist: dabax
